barlaman/__init__.py
barlaman/deputy.py
barlaman/questions.py
barlaman/schedule.py
barlaman/transcript.py
barlaman/utils.py
barlaman/data/__init__.py
barlaman-0.1.3.dist-info/LICENSE.txt
barlaman-0.1.3.dist-info/METADATA
barlaman-0.1.3.dist-info/WHEEL
barlaman-0.1.3.dist-info/top_level.txt
barlaman-0.1.3.dist-info/RECORD
