Metadata-Version: 2.1
Name: barlaman
Version: 0.1.3
Summary: Scrape data of Moroccan House of Representatives.
Home-page: https://github.com/nowabindata/barlaman
Author: ANDAM Amine
Author-email: andamamine83@gmail.com
Keywords: politics,parliament,webscraping,parliamentary-data,morocco
Classifier: Programming Language :: Python :: 3
Classifier: License :: OSI Approved :: MIT License
Classifier: Operating System :: OS Independent
Requires-Python: >=3.6
License-File: LICENSE.txt
